noetl/__init__.py
noetl/main.py
noetl/cli/__init__.py
noetl/cli/ctl.py
noetl/core/__init__.py
noetl/core/common.py
noetl/core/config.py
noetl/core/keyval.py
noetl/core/logger.py
noetl/core/logging_context.py
noetl/core/secret.py
noetl/core/status.py
noetl/core/victorialogs_handler.py
noetl/core/victorialogs_handler_demo.py
noetl/core/auth/__init__.py
noetl/core/auth/constants.py
noetl/core/auth/duckdb.py
noetl/core/auth/google_provider.py
noetl/core/auth/http.py
noetl/core/auth/ib_provider.py
noetl/core/auth/normalize.py
noetl/core/auth/postgres.py
noetl/core/auth/providers.py
noetl/core/auth/resolver.py
noetl/core/auth/token_resolver.py
noetl/core/auth/utils.py
noetl/core/db/__init__.py
noetl/core/db/pool.py
noetl/core/dsl/__init__.py
noetl/core/dsl/normalize.py
noetl/core/dsl/render.py
noetl/core/dsl/schema.py
noetl/core/dsl/v2/__init__.py
noetl/core/dsl/v2/engine.py
noetl/core/dsl/v2/models.py
noetl/core/dsl/v2/parser.py
noetl/core/messaging/__init__.py
noetl/core/messaging/nats_client.py
noetl/core/runtime/__init__.py
noetl/core/runtime/context.py
noetl/core/runtime/events.py
noetl/core/runtime/execution.py
noetl/core/runtime/executor.py
noetl/core/runtime/loop.py
noetl/core/runtime/registry.py
noetl/core/runtime/retry.py
noetl/core/runtime/router.py
noetl/core/runtime/sql.py
noetl/core/scheduler/__init__.py
noetl/core/scheduler/cp_sat_scheduler.py
noetl/core/scheduler/dispatcher.py
noetl/core/scheduler/duration_model.py
noetl/core/scheduler/plan_builder.py
noetl/core/scheduler/plan_types.py
noetl/core/script/__init__.py
noetl/core/script/resolver.py
noetl/core/script/validation.py
noetl/core/script/sources/__init__.py
noetl/core/script/sources/file.py
noetl/core/script/sources/gcs.py
noetl/core/script/sources/http.py
noetl/core/script/sources/s3.py
noetl/core/secrets/__init__.py
noetl/core/secrets/executor.py
noetl/core/secrets/wrapper.py
noetl/core/storage/__init__.py
noetl/core/storage/config.py
noetl/core/storage/duckdb.py
noetl/core/storage/executor.py
noetl-2.4.0.dist-info/licenses/LICENSE
noetl-2.4.0.dist-info/METADATA
noetl-2.4.0.dist-info/WHEEL
noetl-2.4.0.dist-info/entry_points.txt
noetl-2.4.0.dist-info/top_level.txt
noetl-2.4.0.dist-info/RECORD
